{"users":{"a7962556-3fc6-4fe6-89a1-215d9bb536d1":{"user_id":"user_1761757922725_290c688e","session_id":"a7962556-3fc6-4fe6-89a1-215d9bb536d1","device_id":"ca3087bffaaaa321","device_model":"Infinix X6532","android_version":"14","login_time":"2025-10-30 01:14:54","app_version":"1.0","is_first_launch":false},"ed322fe9-6885-4936-aa4a-81333f4131a4":{"user_id":"user_1761757922725_290c688e","session_id":"ed322fe9-6885-4936-aa4a-81333f4131a4","device_id":"ca3087bffaaaa321","device_model":"Infinix X6532","android_version":"14","login_time":"2025-10-30 01:19:47","app_version":"1.0","is_first_launch":false},"43df0b59-19e5-476c-8e09-3ee50ec25508":{"user_id":"user_1761757922725_290c688e","session_id":"43df0b59-19e5-476c-8e09-3ee50ec25508","device_id":"ca3087bffaaaa321","device_model":"Infinix X6532","android_version":"14","login_time":"2025-10-30 01:20:51","app_version":"1.0","is_first_launch":false}},"last_updated":"2025-10-30 01:20:52"}