{
  "app_name": "DarkSilentXP",
  "created_at": "2025-10-31 19:43:16",
  "users": [
    {
      "user_id": "user_1761817657330_9bb9423b",
      "session_id": "b29137ba-1af3-42b5-a3b3-2c19cda12a0e",
      "device_id": "ba87f72cf9c3f031",
      "device_model": "V2120",
      "android_version": "12",
      "login_time": "2025-10-31 19:42:38",
      "app_version": "1.0",
      "is_first_launch": false
    },
    {
      "user_id": "user_1761886514119_049fc44e",
      "session_id": "19691fee-7b5c-4dfb-9075-6d672969e23c",
      "device_id": "ca3087bffaaaa321",
      "device_model": "Infinix X6532",
      "android_version": "14",
      "login_time": "2025-10-31 20:45:31",
      "app_version": "1.0",
      "is_first_launch": false
    },
    {
      "user_id": "user_1761886514119_049fc44e",
      "session_id": "053f7d68-debf-4db1-a04e-eb5bd8e245ff",
      "device_id": "ca3087bffaaaa321",
      "device_model": "Infinix X6532",
      "android_version": "14",
      "login_time": "2025-10-31 20:54:13",
      "app_version": "1.0",
      "is_first_launch": false
    },
    {
      "user_id": "user_1761886514119_049fc44e",
      "session_id": "e5540edb-29ab-4aee-af8c-37d862d730fd",
      "device_id": "ca3087bffaaaa321",
      "device_model": "Infinix X6532",
      "android_version": "14",
      "login_time": "2025-10-31 20:55:42",
      "app_version": "1.0",
      "is_first_launch": false
    },
    {
      "user_id": "user_1761886514119_049fc44e",
      "session_id": "8746f673-2e63-4dc2-a083-2e98628b37f0",
      "device_id": "ca3087bffaaaa321",
      "device_model": "Infinix X6532",
      "android_version": "14",
      "login_time": "2025-10-31 21:01:00",
      "app_version": "1.0",
      "is_first_launch": false
    },
    {
      "user_id": "user_1761759828675_21d4f117",
      "session_id": "18c2dd04-b5d8-4690-b7dd-c149bcb103d5",
      "device_id": "5ef332e57a6f37e1",
      "device_model": "2409BRN2CY",
      "android_version": "14",
      "login_time": "2025-10-31 20:01:15",
      "app_version": "1.0",
      "is_first_launch": false
    },
    {
      "user_id": "user_1761915803558_a1d7e526",
      "session_id": "b8de9802-2621-4f6c-9473-e1f8e18c3a87",
      "device_id": "d25b7322b3324e9f",
      "device_model": "RMX3191",
      "android_version": "13",
      "login_time": "2025-10-31 21:03:23",
      "app_version": "1.0",
      "is_first_launch": true
    },
    {
      "user_id": "user_1761926689428_520ce127",
      "session_id": "be48f742-e3b0-4082-b507-88c6c8bc49f1",
      "device_id": "43fb6068b305d860",
      "device_model": "SM-T555",
      "android_version": "7.1.2",
      "login_time": "2025-10-31 16:04:49",
      "app_version": "1.0",
      "is_first_launch": true
    },
    {
      "user_id": "user_1761926689428_520ce127",
      "session_id": "1abbf7e5-fb95-4805-b57b-f6488942183b",
      "device_id": "43fb6068b305d860",
      "device_model": "SM-T555",
      "android_version": "7.1.2",
      "login_time": "2025-10-31 16:04:56",
      "app_version": "1.0",
      "is_first_launch": false
    },
    {
      "user_id": "user_1761926689428_520ce127",
      "session_id": "21325e2d-83f4-4aec-a456-c2a51a9cdf0b",
      "device_id": "43fb6068b305d860",
      "device_model": "SM-T555",
      "android_version": "7.1.2",
      "login_time": "2025-10-31 16:05:48",
      "app_version": "1.0",
      "is_first_launch": false
    },
    {
      "user_id": "user_1761886514119_049fc44e",
      "session_id": "1f8b13c1-430e-4ce1-aa7e-f0081bdcc4a8",
      "device_id": "ca3087bffaaaa321",
      "device_model": "Infinix X6532",
      "android_version": "14",
      "login_time": "2025-10-31 21:32:09",
      "app_version": "1.0",
      "is_first_launch": false
    },
    {
      "user_id": "user_1761917650094_21b1443b",
      "session_id": "ce9f7c47-ed84-4e92-bb6a-637a589dd31b",
      "device_id": "a74ecbd4a18d8c8a",
      "device_model": "CPH2473",
      "android_version": "14",
      "login_time": "2025-10-31 20:34:10",
      "app_version": "1.0",
      "is_first_launch": true
    },
    {
      "user_id": "user_1761886514119_049fc44e",
      "session_id": "9900b65f-d283-44ae-be85-3d2453da2f76",
      "device_id": "ca3087bffaaaa321",
      "device_model": "Infinix X6532",
      "android_version": "14",
      "login_time": "2025-10-31 21:36:03",
      "app_version": "1.0",
      "is_first_launch": false
    },
    {
      "user_id": "user_1761918619703_0e7cc175",
      "session_id": "0cc8e346-c790-4d2b-bc9d-3f5dbe9642d9",
      "device_id": "ba87f72cf9c3f031",
      "device_model": "V2120",
      "android_version": "12",
      "login_time": "2025-10-31 20:50:19",
      "app_version": "1.0",
      "is_first_launch": true
    },
    {
      "user_id": "user_1761915803558_a1d7e526",
      "session_id": "8376428f-317a-481d-b458-7a40744d2d9d",
      "device_id": "d25b7322b3324e9f",
      "device_model": "RMX3191",
      "android_version": "13",
      "login_time": "2025-10-31 21:52:28",
      "app_version": "1.0",
      "is_first_launch": false
    },
    {
      "user_id": "user_1761886514119_049fc44e",
      "session_id": "2a41b76d-c1b9-49ca-9c85-75e26447a795",
      "device_id": "ca3087bffaaaa321",
      "device_model": "Infinix X6532",
      "android_version": "14",
      "login_time": "2025-10-31 21:52:51",
      "app_version": "1.0",
      "is_first_launch": false
    },
    {
      "user_id": "user_1761915803558_a1d7e526",
      "session_id": "f29b6144-e723-4c83-9487-42470725ab65",
      "device_id": "d25b7322b3324e9f",
      "device_model": "RMX3191",
      "android_version": "13",
      "login_time": "2025-10-31 21:54:27",
      "app_version": "1.0",
      "is_first_launch": false
    },
    {
      "user_id": "user_1761919399740_3e009c28",
      "session_id": "15f1e112-1011-4798-9552-f5119aff6110",
      "device_id": "590638e4de01b4d7",
      "device_model": "SM-A507FN",
      "android_version": "9",
      "login_time": "2025-10-31 21:03:19",
      "app_version": "1.0",
      "is_first_launch": true
    },
    {
      "user_id": "user_1761919399740_3e009c28",
      "session_id": "2d686cd7-6ec0-4dfb-86d1-c8bbae1f7828",
      "device_id": "590638e4de01b4d7",
      "device_model": "SM-A507FN",
      "android_version": "9",
      "login_time": "2025-10-31 21:06:35",
      "app_version": "1.0",
      "is_first_launch": false
    },
    {
      "user_id": "user_1761920749998_dcbfb6c1",
      "session_id": "fecfe38b-0ae1-4fbf-9323-5ec4e50af290",
      "device_id": "00cbfa511fda0637",
      "device_model": "Infinix X6739",
      "android_version": "14",
      "login_time": "2025-10-31 21:25:50",
      "app_version": "1.0",
      "is_first_launch": true
    },
    {
      "user_id": "user_1761920749998_dcbfb6c1",
      "session_id": "e3d62a37-8dd8-489b-a23b-306c5ea8c61b",
      "device_id": "00cbfa511fda0637",
      "device_model": "Infinix X6739",
      "android_version": "14",
      "login_time": "2025-10-31 21:27:26",
      "app_version": "1.0",
      "is_first_launch": false
    },
    {
      "user_id": "user_1761921096568_58f974f6",
      "session_id": "2a09a3f1-1aa7-43d1-af65-a80b2aeada8c",
      "device_id": "3259ea81ae51bb2f",
      "device_model": "V2507",
      "android_version": "15",
      "login_time": "2025-10-31 21:31:36",
      "app_version": "1.0",
      "is_first_launch": true
    },
    {
      "user_id": "user_1761920749998_dcbfb6c1",
      "session_id": "2c499741-1bde-4173-a16e-9d7904d4889a",
      "device_id": "00cbfa511fda0637",
      "device_model": "Infinix X6739",
      "android_version": "14",
      "login_time": "2025-10-31 21:32:19",
      "app_version": "1.0",
      "is_first_launch": false
    },
    {
      "user_id": "user_1761806739248_238f5e09",
      "session_id": "2cb2deb7-7787-48bb-b87f-a3619e11c2c0",
      "device_id": "a79c44c0e0c0368e",
      "device_model": "CPH1723",
      "android_version": "7.1.1",
      "login_time": "2025-10-31 21:46:13",
      "app_version": "1.0",
      "is_first_launch": false
    },
    {
      "user_id": "user_1761806739248_238f5e09",
      "session_id": "2acac1b4-0396-447b-abde-1c0486c42844",
      "device_id": "a79c44c0e0c0368e",
      "device_model": "CPH1723",
      "android_version": "7.1.1",
      "login_time": "2025-10-31 21:46:31",
      "app_version": "1.0",
      "is_first_launch": false
    },
    {
      "user_id": "user_1761806739248_238f5e09",
      "session_id": "d0076364-8cbc-4504-8832-b943f9a69721",
      "device_id": "a79c44c0e0c0368e",
      "device_model": "CPH1723",
      "android_version": "7.1.1",
      "login_time": "2025-10-31 21:46:42",
      "app_version": "1.0",
      "is_first_launch": false
    },
    {
      "user_id": "user_1761806739248_238f5e09",
      "session_id": "42298a9d-a04e-4789-826d-95cbbcf8c396",
      "device_id": "a79c44c0e0c0368e",
      "device_model": "CPH1723",
      "android_version": "7.1.1",
      "login_time": "2025-10-31 21:47:35",
      "app_version": "1.0",
      "is_first_launch": false
    },
    {
      "user_id": "user_1761806739248_238f5e09",
      "session_id": "135ae21d-dbca-419b-8237-57be3f62f200",
      "device_id": "a79c44c0e0c0368e",
      "device_model": "CPH1723",
      "android_version": "7.1.1",
      "login_time": "2025-10-31 21:50:50",
      "app_version": "1.0",
      "is_first_launch": false
    },
    {
      "user_id": "user_1761921096568_58f974f6",
      "session_id": "2ce30ecd-c0d4-49d0-a42a-4aae6e050fce",
      "device_id": "3259ea81ae51bb2f",
      "device_model": "V2507",
      "android_version": "15",
      "login_time": "2025-10-31 21:51:08",
      "app_version": "1.0",
      "is_first_launch": false
    },
    {
      "user_id": "user_1761915803558_a1d7e526",
      "session_id": "b6dba612-3279-48e2-a3e4-101167909b3a",
      "device_id": "d25b7322b3324e9f",
      "device_model": "RMX3191",
      "android_version": "13",
      "login_time": "2025-10-31 22:57:01",
      "app_version": "1.0",
      "is_first_launch": false
    },
    {
      "user_id": "user_1761915803558_a1d7e526",
      "session_id": "835c7bb3-463e-41b5-aa31-f493609f2d2d",
      "device_id": "d25b7322b3324e9f",
      "device_model": "RMX3191",
      "android_version": "13",
      "login_time": "2025-10-31 22:58:53",
      "app_version": "1.0",
      "is_first_launch": false
    },
    {
      "user_id": "user_1761919399740_3e009c28",
      "session_id": "b1018fe3-f572-450f-bc15-9e9caf7abfec",
      "device_id": "590638e4de01b4d7",
      "device_model": "SM-A507FN",
      "android_version": "9",
      "login_time": "2025-10-31 21:58:57",
      "app_version": "1.0",
      "is_first_launch": false
    },
    {
      "user_id": "user_1761915803558_a1d7e526",
      "session_id": "8354a6c5-e8c6-45a8-a122-c2d101b09a6d",
      "device_id": "d25b7322b3324e9f",
      "device_model": "RMX3191",
      "android_version": "13",
      "login_time": "2025-10-31 23:00:21",
      "app_version": "1.0",
      "is_first_launch": false
    },
    {
      "user_id": "user_1761915803558_a1d7e526",
      "session_id": "12cdc6f3-0663-442d-b141-9d2766fa71b9",
      "device_id": "d25b7322b3324e9f",
      "device_model": "RMX3191",
      "android_version": "13",
      "login_time": "2025-10-31 23:15:08",
      "app_version": "1.0",
      "is_first_launch": false
    },
    {
      "user_id": "user_1761924137388_e58fe66b",
      "session_id": "2dc5906c-49dd-4423-8910-41b781b3400f",
      "device_id": "d25b7322b3324e9f",
      "device_model": "RMX3191",
      "android_version": "13",
      "login_time": "2025-10-31 23:22:17",
      "app_version": "1.0",
      "is_first_launch": true
    },
    {
      "user_id": "user_1761924454447_0bc918be",
      "session_id": "3cf9c520-bddd-491a-8521-09c93ada0e01",
      "device_id": "3d68004c6834c323",
      "device_model": "Infinix X6837",
      "android_version": "13",
      "login_time": "2025-10-31 22:27:34",
      "app_version": "1.0",
      "is_first_launch": true
    },
    {
      "user_id": "user_1761809505872_a204cf32",
      "session_id": "ed67c766-01ed-4e89-984f-39df7a75af1e",
      "device_id": "5458003313d3414a",
      "device_model": "vivo 1904",
      "android_version": "11",
      "login_time": "2025-10-31 22:40:47",
      "app_version": "1.0",
      "is_first_launch": false
    },
    {
      "user_id": "user_1761925268863_4a68ca70",
      "session_id": "428d9900-cac7-47ef-b8b7-83fe6f4845a7",
      "device_id": "ff90a9174d566568",
      "device_model": "CPH2641",
      "android_version": "15",
      "login_time": "2025-10-31 23:41:08",
      "app_version": "1.0",
      "is_first_launch": true
    },
    {
      "user_id": "user_1761886514119_049fc44e",
      "session_id": "6f4d81cc-1ca5-44c6-8a56-4919a686a0b1",
      "device_id": "ca3087bffaaaa321",
      "device_model": "Infinix X6532",
      "android_version": "14",
      "login_time": "2025-10-31 23:42:42",
      "app_version": "1.0",
      "is_first_launch": false
    }
  ],
  "last_updated": "2025-10-31 23:42:42"
}